{
    "band": "delta",
    "ch_names": [
        "RFS1",
        "RFS2",
        "RFS3",
        "RFS4",
        "RFS5",
        "RFS6",
        "RPG1",
        "RPG2",
        "RPG5",
        "RPG6",
        "RPG8",
        "RPG9",
        "RPG10",
        "RPG11",
        "RPG12",
        "RPG13",
        "RPG14",
        "RPG15",
        "RPG3",
        "RPG4",
        "RPG16",
        "RPG17",
        "RPG18",
        "RPG19",
        "RPG20",
        "RPG21",
        "RPG22",
        "RPG23",
        "RPG24",
        "RPG25",
        "RPG26",
        "RPG27",
        "RPG28",
        "RPG29",
        "RPG30",
        "RPG31",
        "RPG32",
        "RPG33",
        "RPG34",
        "RPG36",
        "RPG37",
        "RPG38",
        "RPG40",
        "RPG41",
        "RPG42",
        "RPG43",
        "RPG44",
        "RPG45",
        "RPG46",
        "RPG47",
        "RPG48",
        "PSI1",
        "PSI2",
        "PSI3",
        "PSI4",
        "PSI5",
        "PSI6",
        "PSI7",
        "PSI8",
        "PDI1",
        "PDI2",
        "PDI3",
        "PDI4",
        "ASI1",
        "ASI2",
        "ASI3",
        "ASI4",
        "ASI5",
        "ASI6",
        "APD1",
        "APD2",
        "APD3",
        "APD4",
        "APD5",
        "APD6",
        "APD7",
        "APD8",
        "PPD1",
        "PPD2",
        "PPD3",
        "PPD4",
        "PPD5",
        "PPD6",
        "PPD7",
        "PPD8"
    ],
    "clin_onset_event_id": null,
    "events": [
        [
            0,
            0,
            1
        ],
        [
            0,
            0,
            10
        ],
        [
            113,
            0,
            4
        ],
        [
            113,
            0,
            8
        ],
        [
            117,
            0,
            5
        ],
        [
            117,
            0,
            13
        ],
        [
            125,
            0,
            6
        ],
        [
            125,
            0,
            14
        ],
        [
            127,
            0,
            7
        ],
        [
            127,
            0,
            11
        ],
        [
            213,
            0,
            2
        ],
        [
            213,
            0,
            12
        ],
        [
            309,
            0,
            3
        ],
        [
            309,
            0,
            9
        ]
    ],
    "events_id": {
        "+0.000000": 1,
        "+109.000000": 2,
        "+157.000000": 3,
        "+59.000000": 4,
        "+61.000000": 5,
        "+65.000000": 6,
        "+66.000000": 7,
        "SZ EVENT # (PB SZ)": 8,
        "Schedule": 9,
        "Segment: REC START ALL BP EEG": 10,
        "Z MAX SPIKING GRID": 11,
        "Z OVER": 12,
        "Z SPIKES RPG 4/12 AS": 13,
        "z awakens": 14
    },
    "fmax": 4,
    "fmin": 2.0,
    "length_recording": 172172,
    "model_params": {
        "stepsize": 500,
        "winsize": 2500
    },
    "n_wins": 340,
    "output_fname": "sub-jh105_ses-presurgery_task-ictal_acq-ecog_run-04_proc-coh_freq-delta_ieeg.npz",
    "output_fpath": "/home/adam2392/hdd/derivatives/coherence/average/delta/jh105/sub-jh105_ses-presurgery_task-ictal_acq-ecog_run-04_proc-coh_freq-delta_ieeg.npz",
    "reference": "average",
    "sfreq": 1000.0,
    "spectral_connectivity_matrix_shape": [
        85,
        85,
        340
    ],
    "sz_offset_event_id": 12,
    "sz_onset_event_id": 8
}