{
    "band": "beta",
    "ch_names": [
        "ABT1",
        "ABT2",
        "ABT3",
        "ABT4",
        "MBT1",
        "MBT2",
        "MBT3",
        "MBT4",
        "PBT3",
        "PBT4",
        "RAD1",
        "RAD2",
        "RAD3",
        "RAD4",
        "RAD5",
        "RAD6",
        "RAD7",
        "PBT1",
        "PBT2",
        "RHD1",
        "RHD2",
        "RHD3",
        "RHD4",
        "RHD5",
        "RHD6",
        "RHD7",
        "RHD8",
        "RHD9",
        "RTG1",
        "RTG2",
        "RTG3",
        "RTG4",
        "RTG5",
        "RTG6",
        "RTG7",
        "RTG8",
        "RTG9",
        "RTG10",
        "RTG11",
        "RTG12",
        "RTG13",
        "RTG14",
        "RTG15",
        "RTG16",
        "RTG17",
        "RTG19",
        "RTG20",
        "RTG23",
        "RTG24",
        "RTG25",
        "RTG27",
        "RTG28",
        "RTG29",
        "RTG30",
        "RTG31",
        "RTG32",
        "RTG33",
        "RTG34",
        "RTG35",
        "RTG36",
        "RTG37",
        "RTG38",
        "RTG39",
        "RTG40",
        "RTG41",
        "RTG42",
        "RTG43",
        "RTG44",
        "RTG45",
        "RTG46",
        "RTG47",
        "RTG48",
        "RTG49",
        "RTG50",
        "RTG51",
        "RTG52",
        "RTG53",
        "RTG54",
        "RTG55",
        "RTG56",
        "RTG57",
        "RTG58",
        "RTG59",
        "RTG60",
        "RTG61",
        "RTG62",
        "RTG63",
        "RTG64"
    ],
    "clin_onset_event_id": null,
    "events": [
        [
            0,
            0,
            1
        ],
        [
            0,
            0,
            24
        ],
        [
            0,
            0,
            21
        ],
        [
            115,
            0,
            8
        ],
        [
            115,
            0,
            22
        ],
        [
            119,
            0,
            9
        ],
        [
            119,
            0,
            38
        ],
        [
            119,
            0,
            39
        ],
        [
            125,
            0,
            10
        ],
        [
            125,
            0,
            37
        ],
        [
            133,
            0,
            11
        ],
        [
            133,
            0,
            33
        ],
        [
            137,
            0,
            12
        ],
        [
            137,
            0,
            35
        ],
        [
            155,
            0,
            13
        ],
        [
            155,
            0,
            40
        ],
        [
            159,
            0,
            14
        ],
        [
            159,
            0,
            29
        ],
        [
            161,
            0,
            15
        ],
        [
            161,
            0,
            34
        ],
        [
            163,
            0,
            16
        ],
        [
            163,
            0,
            25
        ],
        [
            167,
            0,
            17
        ],
        [
            167,
            0,
            43
        ],
        [
            185,
            0,
            18
        ],
        [
            185,
            0,
            28
        ],
        [
            187,
            0,
            19
        ],
        [
            187,
            0,
            41
        ],
        [
            191,
            0,
            20
        ],
        [
            191,
            0,
            30
        ],
        [
            205,
            0,
            2
        ],
        [
            205,
            0,
            36
        ],
        [
            217,
            0,
            3
        ],
        [
            217,
            0,
            44
        ],
        [
            231,
            0,
            4
        ],
        [
            231,
            0,
            27
        ],
        [
            231,
            0,
            31
        ],
        [
            245,
            0,
            5
        ],
        [
            245,
            0,
            23
        ],
        [
            245,
            0,
            26
        ],
        [
            273,
            0,
            6
        ],
        [
            273,
            0,
            42
        ],
        [
            315,
            0,
            7
        ],
        [
            315,
            0,
            32
        ]
    ],
    "events_id": {
        "+0.000000": 1,
        "+105.000000": 2,
        "+111.000000": 3,
        "+118.000000": 4,
        "+125.000000": 5,
        "+139.000000": 6,
        "+160.000000": 7,
        "+60.000000": 8,
        "+62.000000": 9,
        "+65.000000": 10,
        "+69.000000": 11,
        "+71.000000": 12,
        "+80.000000": 13,
        "+82.000000": 14,
        "+83.000000": 15,
        "+84.000000": 16,
        "+86.000000": 17,
        "+95.000000": 18,
        "+96.000000": 19,
        "+98.000000": 20,
        "A1+A2 OFF": 21,
        "SZ EVENT # (PB SZ)": 22,
        "Schedule": 23,
        "Segment: REC START REC EEG": 24,
        "Z BLINKING": 25,
        "Z DEVOLUTION": 26,
        "Z DROOLING": 27,
        "Z GENERALIZE": 28,
        "Z ICTAL BUILD": 29,
        "Z OPENS MOUTH, HEAD": 30,
        "Z OXYGEN STARTING": 31,
        "Z POST-ICTAL DEPRESS": 32,
        "Z RHD 39-40, 47-48": 33,
        "Z RHD>RAD": 34,
        "Z RHY ALPHA RHD5": 35,
        "Z SCREAMING": 36,
        "Z SEMIRHY SLOW RHD": 37,
        "Z SLEEPING": 38,
        "Z SPK/SLW RAD, RHD>A": 39,
        "Z SPREAD TO RHD, ABT": 40,
        "Z STIFFENING": 41,
        "Z TURNED ON SIDE": 42,
        "Z TURNS HEAD TO LEFT": 43,
        "Z WHOLE BODY CLONIC": 44
    },
    "fmax": 30,
    "fmin": 13,
    "length_recording": 206172,
    "model_params": {
        "stepsize": 500,
        "winsize": 2500
    },
    "n_wins": 408,
    "output_fname": "sub-jh103_ses-presurgery_task-ictal_acq-ecog_run-01_proc-coh_freq-beta_ieeg.npz",
    "output_fpath": "/home/adam2392/hdd/derivatives/coherence/average/jh103/sub-jh103_ses-presurgery_task-ictal_acq-ecog_run-01_proc-coh_freq-beta_ieeg.npz",
    "reference": "average",
    "sfreq": 1000.0,
    "spectral_connectivity_matrix_shape": [
        88,
        88,
        408
    ],
    "sz_offset_event_id": null,
    "sz_onset_event_id": 22
}