{
    "ch_names": [
        "P1",
        "P2",
        "P3",
        "P4",
        "P5",
        "P11",
        "P12",
        "P13",
        "P14",
        "P15",
        "X1",
        "X2",
        "X3",
        "P10",
        "X11",
        "X12",
        "X13",
        "X14",
        "X15",
        "U3",
        "U5",
        "U6",
        "U7",
        "U8",
        "U9",
        "T1",
        "T2",
        "T3",
        "T4",
        "T5",
        "T6",
        "T7",
        "T8",
        "A1",
        "A2",
        "A3",
        "A4",
        "A5",
        "A6",
        "A10",
        "A11",
        "A12",
        "A13",
        "A14",
        "I7",
        "I8",
        "S2",
        "S3",
        "S4",
        "S5",
        "S6",
        "S7",
        "S8",
        "S9",
        "S10",
        "Q1",
        "Q2",
        "Q3",
        "Q4",
        "Q5",
        "Q6",
        "Q7",
        "Q8",
        "Q9",
        "O1",
        "O2",
        "O7",
        "O8",
        "O9",
        "O10",
        "O11",
        "O12",
        "O13",
        "G1",
        "G2",
        "G3",
        "G4",
        "T'1",
        "T'2",
        "T'3",
        "T'4",
        "T'5",
        "T'6",
        "T'7",
        "T'8",
        "T'9",
        "S'2",
        "S'3",
        "S'4",
        "S'5",
        "S'6",
        "S'7",
        "S'8",
        "S'9",
        "S'10",
        "Q'2",
        "Q'3",
        "Q'7",
        "Q'8"
    ],
    "clinonset_win": null,
    "delta_vectors_shape": [
        99,
        99,
        2496
    ],
    "events": [
        [
            0,
            0,
            1
        ],
        [
            0,
            0,
            20
        ],
        [
            31,
            0,
            11
        ],
        [
            31,
            0,
            16
        ],
        [
            91,
            0,
            2
        ],
        [
            91,
            0,
            19
        ],
        [
            102,
            0,
            3
        ],
        [
            102,
            0,
            18
        ],
        [
            130,
            0,
            4
        ],
        [
            130,
            0,
            21
        ],
        [
            134,
            0,
            5
        ],
        [
            134,
            0,
            17
        ],
        [
            138,
            0,
            6
        ],
        [
            138,
            0,
            29
        ],
        [
            139,
            0,
            7
        ],
        [
            139,
            0,
            26
        ],
        [
            172,
            0,
            8
        ],
        [
            172,
            0,
            27
        ],
        [
            212,
            0,
            9
        ],
        [
            212,
            0,
            28
        ],
        [
            306,
            0,
            10
        ],
        [
            306,
            0,
            25
        ],
        [
            353,
            0,
            12
        ],
        [
            353,
            0,
            22
        ],
        [
            358,
            0,
            13
        ],
        [
            358,
            0,
            24
        ],
        [
            364,
            0,
            14
        ],
        [
            364,
            0,
            30
        ],
        [
            551,
            0,
            15
        ],
        [
            551,
            0,
            23
        ]
    ],
    "events_id": {
        "+0.000000": 1,
        "+11.608000": 2,
        "+13.006000": 3,
        "+16.619000": 4,
        "+16.976000": 5,
        "+17.460000": 6,
        "+17.641000": 7,
        "+21.691000": 8,
        "+26.792000": 9,
        "+38.555000": 10,
        "+4.200000": 11,
        "+44.450000": 12,
        "+45.122000": 13,
        "+45.729000": 14,
        "+69.241000": 15,
        "A1+A2 OFF": 16,
        "Clinical onset": 17,
        "EEG onset": 18,
        "SZ 1P": 19,
        "Segment: REC START Tech-Bi EE": 20,
        "Tachycardia": 21,
        "X": 22,
        "bkgd suppression X/A": 23,
        "end": 24,
        "hr 102": 25,
        "jaw clonic": 26,
        "left arm clonic": 27,
        "left head deviation": 28,
        "opens eyes": 29,
        "postictal bkgd suppr": 30
    },
    "length_recording": 312145,
    "model_params": {
        "method_to_use": "pinv",
        "numcores": 20,
        "perturbtype": "C",
        "radius": 1.5,
        "sfreq": 1000.0,
        "stepsize": 125,
        "tempdir": "/home/adam2392/hdd/derivatives/fragility/average/nl19/sub-nl19_ses-presurgery_task-ictal_acq-seeg_run-01_proc-fragility_average_ieeg-tempdir",
        "winsize": 250
    },
    "numwins": 2496,
    "offsetwin": null,
    "onsetwin": null,
    "output_fpath": "/home/adam2392/hdd/derivatives/fragility/average/nl19/sub-nl19_ses-presurgery_task-ictal_acq-seeg_run-01_proc-fragility_average_ieeg.npz",
    "perturbation_matrix_shape": [
        99,
        2496
    ],
    "reference": "average",
    "sfreq": 1000.0,
    "state_matrix_shape": [
        99,
        99,
        2496
    ]
}