{
    "band": "gamma",
    "ch_names": [
        "RAM4",
        "RAM5",
        "RAM6",
        "RAM7",
        "RAL5",
        "RAL6",
        "RAL7",
        "RG3",
        "RG4",
        "RG5",
        "RG6",
        "RG7",
        "RG8",
        "RG9",
        "RG10",
        "RG11",
        "RG12",
        "RG13",
        "RG1",
        "RG2",
        "RG14",
        "RG15",
        "RG16",
        "RG17",
        "RG18",
        "RG19",
        "RG20",
        "RG21",
        "RG22",
        "RG23",
        "RG24",
        "RG26",
        "RG27",
        "RG28",
        "RG29",
        "RG30",
        "RG31",
        "RG32",
        "RG33",
        "RG34",
        "RG35",
        "RG36",
        "RG37",
        "RG38",
        "RG39",
        "RG40",
        "RG41",
        "RG42",
        "RG43",
        "RG44",
        "RG45",
        "RG46",
        "RG47",
        "RG48",
        "RPG12",
        "RPG11",
        "RPG10",
        "RPG9",
        "RGP8",
        "RPG7",
        "RPG6",
        "RPG5",
        "RPG4",
        "RPG3",
        "RPG2",
        "RPG1",
        "LG1",
        "LG2",
        "LG3",
        "LG4",
        "LG5",
        "LG6",
        "LG7",
        "LG8",
        "LG9",
        "LG10",
        "LG11",
        "LG12"
    ],
    "clin_onset_event_id": null,
    "clin_onset_win": null,
    "events": [
        [
            0,
            0,
            1
        ],
        [
            0,
            0,
            5
        ],
        [
            0,
            0,
            4
        ],
        [
            147,
            0,
            3
        ],
        [
            147,
            0,
            7
        ],
        [
            363,
            0,
            2
        ],
        [
            363,
            0,
            6
        ]
    ],
    "events_id": {
        "+0.000000": 1,
        "+183.718000": 2,
        "+75.760000": 3,
        "A1+A2 OFF": 4,
        "Segment: REC START Harmon Ref": 5,
        "offset": 6,
        "onset": 7
    },
    "fmax": 90,
    "fmin": 30,
    "length_recording": 249090,
    "model_params": {
        "stepsize": 500,
        "winsize": 2500
    },
    "n_wins": 494,
    "output_fname": "sub-pt11_ses-presurgery_task-ictal_acq-ecog_run-02_proc-cohdegree_freq-gamma_ieeg.npz",
    "output_fpath": "/home/adam2392/hdd/derivatives/coherence-degree/average/pt11/sub-pt11_ses-presurgery_task-ictal_acq-ecog_run-02_proc-cohdegree_freq-gamma_ieeg.npz",
    "reference": "average",
    "sfreq": 1000.0,
    "spectral_connectivity_matrix_shape": [
        78,
        78,
        494
    ],
    "sz_offset_event_id": 6,
    "sz_offset_win": 363,
    "sz_onset_event_id": 7,
    "sz_onset_win": 147
}