{
    "band": "highgamma",
    "ch_names": [
        "C1",
        "C2",
        "C3",
        "C4",
        "C5",
        "C6",
        "C7",
        "C8",
        "C9",
        "C10",
        "C11",
        "C12",
        "C13",
        "C14",
        "C15",
        "C16",
        "C17",
        "C18",
        "C19",
        "C20",
        "C21",
        "C22",
        "C23",
        "C24",
        "C25",
        "C26",
        "C27",
        "C28",
        "C29",
        "C30",
        "C31",
        "C32",
        "C33",
        "C34",
        "C35",
        "C36",
        "C37",
        "C38",
        "C39",
        "C40",
        "C41",
        "C42",
        "C43",
        "C44",
        "C45",
        "C46",
        "C47",
        "C48",
        "C49",
        "C50",
        "C51",
        "C52",
        "C53",
        "C54",
        "C55",
        "C56",
        "C57",
        "C58",
        "C59",
        "C60",
        "C61",
        "C62",
        "C63",
        "C64",
        "BTM1",
        "BTM2",
        "BTM3",
        "BTM4",
        "BTM5",
        "BTM6",
        "BTP1",
        "BTP2",
        "BTP3",
        "BTP4",
        "BTP5",
        "BTP6"
    ],
    "clin_onset_event_id": null,
    "events": [
        [
            0,
            0,
            1
        ]
    ],
    "events_id": {
        "New Segment/": 1
    },
    "fmax": 300,
    "fmin": 90,
    "length_recording": 63070,
    "model_params": {
        "stepsize": 500,
        "winsize": 2500
    },
    "n_wins": 122,
    "output_fname": "sub-umf001_ses-presurgery_task-interictal_acq-ecog_run-02_proc-coh_freq-highgamma_ieeg.npz",
    "output_fpath": "/home/adam2392/hdd/derivatives/coherence/average/umf001/sub-umf001_ses-presurgery_task-interictal_acq-ecog_run-02_proc-coh_freq-highgamma_ieeg.npz",
    "reference": "average",
    "sfreq": 1000.0,
    "spectral_connectivity_matrix_shape": [
        76,
        76,
        122
    ],
    "sz_offset_event_id": null,
    "sz_onset_event_id": null
}